Metadata-Version: 1.0
Name: pjc
Version: 0.2.5.1
Summary: Package for create projects
Home-page: https://github.com/w0rng/project-creator
Author: w0rng
Author-email: UNKNOWN
License: UNKNOWN
Platform: UNKNOWN
